{
"0":"श्लोक २१८ ]",
"1":"प्रथमाह्निकम् ।",
"2":"२४१",
"3":"इह सविकल्पज्ञानात्मनि शाक्तोपाये यद्यपि",
"4":"निर्विकल्पापेक्षया स्फुटे ज्ञानक्रिये, तथापि मातृदौ-",
"5":"रात्म्यात् ते संकुचित एव इति श्रत्रापि उपदे-",
"6":"शादियत्तेन श्रवश्यं भाव्यं येन सर्वस्य तथा",
"7":"संकोचविलायनपरतया सा शाक्ती भूः उज्ज्वला",
"8":"विकस्वरा, यदियम् उपेयत्वेन अभीप्सितम् अन्तः",
"9":"प्रमात्रैकात्म्यस्वभावम् आभासं करोति - परप्रमात्रे -",
"10":"करूपतया स्फुरति इत्यर्थः ॥ २१७॥२१८॥",
"11":"ननु शाक्तस्य शाम्भवाद्विकल्पाविकल्परूपत्वेन",
"12":"सिद्धो भेदः, विकल्पैकरूपात् पुनराणवादस्य कथं भेदः",
"13":"स्यात् ? इत्याशङ्कां प्रदर्श्य, तयोरेव भेदमभिधत्ते ।",
"14":"ननु वैकल्पिकी किं धी-",
"15":"राणवे नास्ति तत्र सा ।",
"16":"अन्योपायात्र तूच्चार -",
"17":"रहितत्वं न्यरूपयत् ॥२२६॥",
"18":"तत्र इत्यादिना समाधिः, अन्य इति उच्चारादयः ।",
"19":"पं० ५ ० पु० विलापनपरतयेति पाठः ।",
"20":"पं० ७ ख० पु० परप्रमात्रैकात्म्यरूपेति पाठः ।",
"21":"पं० १३ क० पु० यत्र सा इति पाठः ।",
"22":"पं० १६ क० पु० मन्त्र इत्यादिनेति पाठः ।",
"23":"३१",
}