{
"0":"१७०",
"1":"श्रीतन्त्रालोकः",
"2":"त्मनि छाद्यत्वे, च्युते - वेद्यवेदकविभागविगलना-",
"3":"त्पूर्णे रूपे समुदिते सति, आमृतं -विकासदशा-",
"4":"मयं तत्त्वं संघट्टे प्रविभाव्यते इति पूर्वेणैव",
"5":"संबन्धः ॥ १७० ॥",
"6":"ननु चास्य स्वाभाविकपूर्ण दृक्रियावरणेऽपि",
"7":"किं निमित्तम् ? इत्याशङ्कयाह",
"8":"व्याप्त्री शक्तिर्विषं यस्मा-",
"9":"व्याप्तुश्छादयेन्महः ।",
"10":"शक्तिरिति - पारमेश्वरी स्वरूपगोपनारूपा मा-",
"11":"याख्या, मह इति - स्वाभाविकपूर्णदृक्क्रियारूपं,",
"12":"विषमपि हि बहिर्व्यापकत्वादव्यासु रण्वात्मनो -",
"13":"विक्रयावरणमेव कुर्यादित्यत्र तदारोपः ॥",
"14":"एवं न केवलमस्य कामतत्त्वत्वमस्ति, विषत-",
"15":"त्वत्वं वा, यावन्निरञ्जनत्वमपि, इत्याह",
"16":"निरञ्जनं परं धाम",
"17":"तत्त्वं तस्य तु साञ्जनम् ॥ १७१ ॥",
"18":"क्रियाशक्त्यात्मकं विश्व-",
"19":"मयं तस्मात्स्फुरेद्यतः ।",
}